unarchiver/__init__.py
unarchiver/unarchiver.py
unarchiver-0.2.0.dist-info/METADATA
unarchiver-0.2.0.dist-info/WHEEL
unarchiver-0.2.0.dist-info/entry_points.txt
unarchiver-0.2.0.dist-info/RECORD
